ogcapi_registry/__init__.py
ogcapi_registry/client.py
ogcapi_registry/exceptions.py
ogcapi_registry/models.py
ogcapi_registry/ogc_registry.py
ogcapi_registry/ogc_types.py
ogcapi_registry/protocols.py
ogcapi_registry/py.typed
ogcapi_registry/registry.py
ogcapi_registry/strategies/__init__.py
ogcapi_registry/strategies/base.py
ogcapi_registry/strategies/common.py
ogcapi_registry/strategies/features.py
ogcapi_registry/strategies/other.py
ogcapi_registry/strategies/processes.py
ogcapi_registry/strategies/records.py
ogcapi_registry/strategies/tiles.py
ogcapi_registry/strategy_registry.py
ogcapi_registry/validator.py
ogcapi_registry-0.3.0.dist-info/WHEEL
ogcapi_registry-0.3.0.dist-info/METADATA
ogcapi_registry-0.3.0.dist-info/RECORD
