Metadata-Version: 2.3
Name: ogcapi-registry
Version: 0.3.0
Summary: A Python library for validating OpenAPI documents published by OGC API servers
Keywords: ogc,ogc-api,openapi,validation,geospatial,features,tiles,processes
Author: Francesco Bartoli
Author-email: Francesco Bartoli <xbartolone@gmail.com>
License: MIT
Classifier: Development Status :: 4 - Beta
Classifier: Intended Audience :: Developers
Classifier: License :: OSI Approved :: MIT License
Classifier: Operating System :: OS Independent
Classifier: Programming Language :: Python :: 3
Classifier: Programming Language :: Python :: 3.11
Classifier: Programming Language :: Python :: 3.12
Classifier: Programming Language :: Python :: 3.13
Classifier: Topic :: Scientific/Engineering :: GIS
Classifier: Topic :: Software Development :: Libraries :: Python Modules
Classifier: Typing :: Typed
Requires-Dist: httpx>=0.28.1
Requires-Dist: openapi-pydantic>=0.5.1
Requires-Dist: pydantic>=2.12.5
Requires-Dist: pyyaml>=6.0.3
Requires-Python: >=3.11
Project-URL: Changelog, https://github.com/francbartoli/ogcapi-registry/blob/main/CHANGELOG.md
Project-URL: Documentation, https://francbartoli.github.io/ogcapi-registry/
Project-URL: Homepage, https://github.com/francbartoli/ogcapi-registry
Project-URL: Issues, https://github.com/francbartoli/ogcapi-registry/issues
Project-URL: Repository, https://github.com/francbartoli/ogcapi-registry
